ofunctions.requestor-1.2.3-py3.12-nspkg.pth
ofunctions/requestor/__init__.py
ofunctions.requestor-1.2.3.dist-info/LICENSE
ofunctions.requestor-1.2.3.dist-info/METADATA
ofunctions.requestor-1.2.3.dist-info/WHEEL
ofunctions.requestor-1.2.3.dist-info/namespace_packages.txt
ofunctions.requestor-1.2.3.dist-info/top_level.txt
ofunctions.requestor-1.2.3.dist-info/RECORD
